hauliopylib/__init__.py
hauliopylib/shared.py
hauliopylib/version.py
hauliopylib/geo/__init__.py
hauliopylib/geo/sg.py
hauliopylib/geo/th.py
hauliopylib-0.40.dist-info/LICENSE
hauliopylib-0.40.dist-info/METADATA
hauliopylib-0.40.dist-info/WHEEL
hauliopylib-0.40.dist-info/top_level.txt
hauliopylib-0.40.dist-info/RECORD
