Metadata-Version: 2.1
Name: hauliopylib
Version: 0.40
Summary: This is a company library.
Home-page: https://hauliov1@dev.azure.com/hauliov1/hauliopylib/_git/hauliopylib
Author: Haulio Pte Ltd
Author-email: data@haulio.io
License: UNKNOWN
Platform: UNKNOWN
Classifier: Programming Language :: Python :: 3
Classifier: License :: OSI Approved :: MIT License
Classifier: Operating System :: OS Independent
Requires-Python: >=3.7
License-File: LICENSE
